Metadata-Version: 2.1
Name: sentry-dingding-maxbon
Version: 1.0.5
Summary: A Sentry extension which send errors stats to DingDing
Home-page: https://github.com/jacksnowfuck/sentry-dingding-maxbon
Author: season
Author-email: zhudetaluo@gmail.com
License: MIT
Keywords: sentry dingding
Platform: UNKNOWN
Classifier: Programming Language :: Python :: 2.7
Classifier: License :: OSI Approved :: MIT License
Requires-Dist: sentry (>=9.0.0)
Requires-Dist: requests
